tuible/__init__.py
tuible/cli.py
tuible/core.py
tuible/params.py
tuible/table.py
tuible-0.2.3.dist-info/METADATA
tuible-0.2.3.dist-info/WHEEL
tuible-0.2.3.dist-info/entry_points.txt
tuible-0.2.3.dist-info/licenses/LICENSE
tuible-0.2.3.dist-info/RECORD
