Metadata-Version: 2.4
Name: tuible
Version: 0.2.3
Summary: A Python package for printing formatted CLI tables with ANSI colors
Project-URL: Homepage, https://github.com/frankausberlin/tuible
Project-URL: Repository, https://github.com/frankausberlin/tuible
Project-URL: Issues, https://github.com/frankausberlin/tuible/issues
Project-URL: Documentation, https://github.com/frankausberlin/tuible#readme
Author-email: Frank <frankbloecher@gmail.com>
License: MIT
License-File: LICENSE
Keywords: ansi,cli,colors,table,terminal
Classifier: Development Status :: 4 - Beta
Classifier: Intended Audience :: Developers
Classifier: License :: OSI Approved :: MIT License
Classifier: Operating System :: OS Independent
Classifier: Programming Language :: Python :: 3
Classifier: Programming Language :: Python :: 3.8
Classifier: Programming Language :: Python :: 3.9
Classifier: Programming Language :: Python :: 3.10
Classifier: Programming Language :: Python :: 3.11
Classifier: Programming Language :: Python :: 3.12
Classifier: Topic :: Terminals
Classifier: Topic :: Utilities
Requires-Python: >=3.8
